deezerpy/__init__.py
deezerpy/auth.py
deezerpy/deezerpy.py
DeezerPy-1.0.dist-info/LICENSE
DeezerPy-1.0.dist-info/METADATA
DeezerPy-1.0.dist-info/WHEEL
DeezerPy-1.0.dist-info/top_level.txt
DeezerPy-1.0.dist-info/RECORD
