Metadata-Version: 2.1
Name: DeezerPy
Version: 1.0
Summary: Wrapper for the Deezer API including authentication
Home-page: https://github.com/NcVillalobos/DeezPy
Author: Nicolas Villalobos
Author-email: developmentvilla@gmail.com
License: UNKNOWN
Platform: UNKNOWN
Classifier: Programming Language :: Python :: 3
Classifier: License :: OSI Approved :: MIT License
Classifier: Operating System :: OS Independent
